django_es_indexer/__init__.py
django_es_indexer/django_es_indexer.py
django_es_indexer-2.1.6.dist-info/DESCRIPTION.rst
django_es_indexer-2.1.6.dist-info/METADATA
django_es_indexer-2.1.6.dist-info/RECORD
django_es_indexer-2.1.6.dist-info/WHEEL
django_es_indexer-2.1.6.dist-info/metadata.json
django_es_indexer-2.1.6.dist-info/top_level.txt
