Metadata-Version: 2.0
Name: django-es-indexer
Version: 2.1.6
Summary: Elasticsearch indexing from a django app
Home-page: https://bitbucket.org/mirusresearch/django_es_indexer
Author: Mirus Research
Author-email: frank@mirusresearch.com
License: MIT license, see LICENSE.txt
Platform: UNKNOWN
Requires-Dist: six (>=1.11.0)
